espressoApi/__init__.py
espressoApi/espressoApiWebsocket.py
espressoApi/espressoConnect.py
espressoApi/espressoExceptions.py
test/__init__.py
test/test_espresso.py
espressoconnect-1.0.0.4.dist-info/METADATA
espressoconnect-1.0.0.4.dist-info/WHEEL
espressoconnect-1.0.0.4.dist-info/top_level.txt
espressoconnect-1.0.0.4.dist-info/RECORD
