Metadata-Version: 2.1
Name: espressoconnect
Version: 1.0.0.4
Summary: Espresso API Server
Home-page: UNKNOWN
Author: rg-espressoapi
Author-email: espressoconnect@myespresso.com
License: UNKNOWN
Platform: UNKNOWN
Classifier: Intended Audience :: Developers
Classifier: Programming Language :: Python
Classifier: Natural Language :: English
Classifier: Programming Language :: Python :: 2.7
Classifier: Programming Language :: Python :: 3.5
Classifier: Programming Language :: Python :: 3.6
Classifier: Programming Language :: Python :: 3.7
Classifier: Topic :: Office/Business :: Financial :: Investment
Classifier: Topic :: Software Development :: Libraries :: Python Modules
Classifier: Topic :: Software Development :: Libraries
Requires-Dist: Crypto
Requires-Dist: cryptography
Requires-Dist: requests (>=2.18.4)
Requires-Dist: six (>=1.11.0)
